lifx/__init__.py
lifx/color.py
lifx/exception.py
lifx/get_selectors.py
lifx/model.py
lifx/scenes.py
lifx/selector.py
lifx/session.py
lifx_wrapper-0.1.4.dist-info/WHEEL
lifx_wrapper-0.1.4.dist-info/METADATA
lifx_wrapper-0.1.4.dist-info/RECORD
